{"RankBranged": {"Str": 5, "HP": 0, "Res": -5, "Luck": 0, "Def": 0, "Spd": -5, "Mag": 5, "Skl": 0}, "Killerweapons": {"Str": 0, "HP": -5, "Res": 0, "Luck": -5, "Def": 5, "Spd": 0, "Mag": 0, "Skl": 5}, "Steelweapons": {"Str": 5, "HP": 5, "Res": 0, "Luck": 0, "Def": -5, "Spd": -5, "Mag": 0, "Skl": 0}, "RankEspells(+light)": {"Str": 0, "HP": 5, "Res": 5, "Luck": 0, "Def": -5, "Spd": 0, "Mag": 0, "Skl": -5}, "RankSWeapons": {"Str": -5, "HP": 0, "Res": 0, "Luck": 5, "Def": 0, "Spd": 0, "Mag": 5, "Skl": -5}, "RankASpells": {"Str": -5, "HP": 0, "Res": 0, "Luck": -5, "Def": 0, "Spd": 5, "Mag": 5, "Skl": 0}, "RankE+Cranged": {"Str": 5, "HP": 5, "Res": 0, "Luck": 0, "Def": -5, "Spd": -5, "Mag": 0, "Skl": 0}, "Slimweapons": {"Str": 0, "HP": 0, "Res": 5, "Luck": 0, "Def": -5, "Spd": 5, "Mag": -5, "Skl": 0}, "Braveweapons": {"Str": 0, "HP": 5, "Res": 0, "Luck": -5, "Def": 0, "Spd": 0, "Mag": -5, "Skl": 5}, "Horse-slaying": {"Str": 0, "HP": -5, "Res": -5, "Luck": 5, "Def": 0, "Spd": 5, "Mag": 0, "Skl": 0}, "Armour-slaying": {"Str": 0, "HP": 0, "Res": 5, "Luck": 0, "Def": 5, "Spd": 0, "Mag": -5, "Skl": -5}, "Other": {"Str": 0, "HP": 0, "Res": 0, "Luck": 0, "Def": 0, "Spd": 0, "Mag": 0, "Skl": 0}, "MagicWeapons": {"Str": -5, "HP": 0, "Res": 5, "Luck": -5, "Def": 0, "Spd": 0, "Mag": 5, "Skl": 0}, "Silverweapons": {"Str": 0, "HP": -5, "Res": 5, "Luck": 5, "Def": 5, "Spd": 0, "Mag": 0, "Skl": -5}, "RankDSpells(+shine)": {"Str": 0, "HP": 0, "Res": 5, "Luck": 0, "Def": -5, "Spd": -5, "Mag": 0, "Skl": 5}, "Ironweapons": {"Str": -5, "HP": 0, "Res": -5, "Luck": 0, "Def": 0, "Spd": 5, "Mag": 0, "Skl": 5}, "LongRangedSpells": {"Str": -5, "HP": -5, "Res": 0, "Luck": 5, "Def": 0, "Spd": 0, "Mag": 5, "Skl": 0}, "RankSSpells": {"Str": -5, "HP": 0, "Res": 5, "Luck": 0, "Def": -5, "Spd": 0, "Mag": 5, "Skl": 0}}